brain_games/__init__.py
brain_games/cli.py
brain_games/games/base_game.py
brain_games/games/calc_game.py
brain_games/games/even_game.py
brain_games/games/gcd_game.py
brain_games/games/prime_game.py
brain_games/games/progression_game.py
brain_games/scripts/__init__.py
brain_games/scripts/brain_calc.py
brain_games/scripts/brain_even.py
brain_games/scripts/brain_games.py
brain_games/scripts/brain_gcd.py
brain_games/scripts/brain_prime.py
brain_games/scripts/brain_progression.py
jkulds_brain_games-0.1.3.dist-info/METADATA
jkulds_brain_games-0.1.3.dist-info/WHEEL
jkulds_brain_games-0.1.3.dist-info/entry_points.txt
jkulds_brain_games-0.1.3.dist-info/RECORD
