Metadata-Version: 2.1
Name: jkulds-brain-games
Version: 0.1.3
Summary: Простой набор головоломок
Home-page: https://github.com/jkulds/python-project-49
Author: jkulds
Author-email: w84my5@yandex.ru
Requires-Python: >=3.10,<4.0
Classifier: Programming Language :: Python :: 3
Classifier: Programming Language :: Python :: 3.10
Classifier: Programming Language :: Python :: 3.11
Classifier: Topic :: Software Development :: Build Tools
Classifier: Topic :: Software Development :: Libraries :: Python Modules
Requires-Dist: prompt (>=0.4.1,<0.5.0)
Project-URL: Repository, https://github.com/jkulds/python-project-49
